pyvjoy/__init__.py
pyvjoy/_sdk.py
pyvjoy/_wrapper.py
pyvjoy/constants.py
pyvjoy/exceptions.py
pyvjoy/vjoydevice.py
pyvjoy/utils/x64/vJoyInterface.dll
pyvjoy/utils/x86/vJoyInterface.dll
pyvjoy-1.0.1.dist-info/LICENSE
pyvjoy-1.0.1.dist-info/METADATA
pyvjoy-1.0.1.dist-info/WHEEL
pyvjoy-1.0.1.dist-info/entry_points.txt
pyvjoy-1.0.1.dist-info/top_level.txt
pyvjoy-1.0.1.dist-info/RECORD
