Metadata-Version: 1.1
Name: pyvjoy
Version: 1.0.1
Summary: Python bindings for vJoy
Home-page: https://github.com/maxofbritton/pyvjoy
Author: Maximilian Britton
Author-email: maximilian.briton@gmail.com
License: MIT
Platform: UNKNOWN
Classifier: Programming Language :: Python :: 3
Classifier: License :: OSI Approved :: MIT License
Classifier: Operating System :: Microsoft :: Windows
